MANIFEST.in
README
img_test.png
setup.py
tornadohttpclient.py
tornadohttpclient.egg-info/PKG-INFO
tornadohttpclient.egg-info/SOURCES.txt
tornadohttpclient.egg-info/dependency_links.txt
tornadohttpclient.egg-info/pbr.json
tornadohttpclient.egg-info/requires.txt
tornadohttpclient.egg-info/top_level.txt