Metadata-Version: 1.1
Name: tornadohttpclient
Version: 0.1.0
Summary: Asynchronous http client.
Home-page: http://www.linuxzen.com
Author: cold
Author-email: wh_linux@126.com
License: Apache 2.0
Platform: any
Classifier: Development Status :: 3 - Alpha
Classifier: Intended Audience :: Developers
Classifier: License :: OSI Approved :: Apache Software License
Classifier: Topic :: Internet :: WWW/HTTP
Classifier: Programming Language :: Python :: 2.7
Classifier: Programming Language :: Python :: 3
Classifier: Programming Language :: Python :: 3.0
Classifier: Programming Language :: Python :: 3.3
